{"lib\\assets\\images\\Back.png":["lib\\assets\\images\\Back.png","lib/assets/images/Back.png"],"lib\\assets\\images\\Front.png":["lib\\assets\\images\\Front.png","lib/assets/images/Front.png"],"lib\\assets\\images\\avatar.png":["lib\\assets\\images\\avatar.png","lib/assets/images/avatar.png"],"lib\\assets\\images\\background.png":["lib\\assets\\images\\background.png","lib/assets/images/background.png"],"lib\\assets\\images\\baked.png":["lib\\assets\\images\\baked.png","lib/assets/images/baked.png"],"lib\\assets\\images\\bgDetails.png":["lib\\assets\\images\\bgDetails.png","lib/assets/images/bgDetails.png"],"lib\\assets\\images\\donut1.png":["lib\\assets\\images\\donut1.png","lib/assets/images/donut1.png"],"lib\\assets\\images\\donut2.png":["lib\\assets\\images\\donut2.png","lib/assets/images/donut2.png"],"lib\\assets\\images\\donut3.png":["lib\\assets\\images\\donut3.png","lib/assets/images/donut3.png"],"lib\\assets\\images\\donut4.png":["lib\\assets\\images\\donut4.png","lib/assets/images/donut4.png"],"lib\\assets\\images\\donut5.png":["lib\\assets\\images\\donut5.png","lib/assets/images/donut5.png"],"lib\\assets\\images\\donut6.png":["lib\\assets\\images\\donut6.png","lib/assets/images/donut6.png"],"lib\\assets\\images\\donuts.png":["lib\\assets\\images\\donuts.png","lib/assets/images/donuts.png"],"lib\\assets\\images\\donuts2.png":["lib\\assets\\images\\donuts2.png","lib/assets/images/donuts2.png"],"lib\\assets\\images\\fbIcon.png":["lib\\assets\\images\\fbIcon.png","lib/assets/images/fbIcon.png"],"lib/assets/fonts/HT_Pizzeria_W01_Regular.ttf":["lib/assets/fonts/HT_Pizzeria_W01_Regular.ttf"],"lib/assets/fonts/Quicksand-Bold.ttf":["lib/assets/fonts/Quicksand-Bold.ttf"],"lib/assets/fonts/Quicksand-SemiBold.ttf":["lib/assets/fonts/Quicksand-SemiBold.ttf"],"packages/cupertino_icons/assets/CupertinoIcons.ttf":["packages/cupertino_icons/assets/CupertinoIcons.ttf"]}